nb_helpers/__init__.py
nb_helpers/_modidx.py
nb_helpers/actions.py
nb_helpers/clean.py
nb_helpers/colab.py
nb_helpers/docker.py
nb_helpers/export.py
nb_helpers/run.py
nb_helpers/utils.py
nb_helpers/wandb.py
nb_helpers-0.6.2.dist-info/LICENSE
nb_helpers-0.6.2.dist-info/METADATA
nb_helpers-0.6.2.dist-info/WHEEL
nb_helpers-0.6.2.dist-info/entry_points.txt
nb_helpers-0.6.2.dist-info/top_level.txt
nb_helpers-0.6.2.dist-info/RECORD
