Metadata-Version: 2.1
Name: nb-helpers
Version: 0.6.2
Summary: A set of tools for nb handling
Home-page: https://github.com/wandb/nb_helpers/tree/main/
Author: Thomas Capelle
Author-email: tcapelle@wandb.com
License: MIT License
Keywords: jupyter notebook
Platform: UNKNOWN
Classifier: Development Status :: 5 - Production/Stable
Classifier: Intended Audience :: Developers
Classifier: License :: OSI Approved :: MIT License
Classifier: Natural Language :: English
Classifier: Programming Language :: Python :: 3.7
Classifier: Programming Language :: Python :: 3.8
Classifier: Programming Language :: Python :: 3.9
Classifier: Programming Language :: Python :: 3.10
Requires-Python: >=3.7
License-File: LICENSE
Requires-Dist: pip
Requires-Dist: packaging
Requires-Dist: rich
Requires-Dist: fastcore
Requires-Dist: ipython
Requires-Dist: execnb (==0.1.2)
Requires-Dist: ghapi
Requires-Dist: GitPython
Provides-Extra: dev
